README.md
setup.py
bin/kegberry
jrfork_kegberry.egg-info/PKG-INFO
jrfork_kegberry.egg-info/SOURCES.txt
jrfork_kegberry.egg-info/dependency_links.txt
jrfork_kegberry.egg-info/requires.txt
jrfork_kegberry.egg-info/top_level.txt
kegberry/__init__.py
kegberry/app.py
kegberry/templates.py