Metadata-Version: 1.0
Name: jrfork-kegberry
Version: 0.0.6
Summary: Johnnyruzdev fork of the Kegberry Package
Home-page: http://kegberry.kegbot.org/
Author: johnnyruzdev
Author-email: johnnyruzdev01@outlook.com
License: UNKNOWN
Platform: UNKNOWN
